CHANGELOG.md
pycololight/__init__.py
pycololight/constants.py
pycololight/effects.py
pycololight/pycololight.py
pycololight-2.1.0.dist-info/LICENSE
pycololight-2.1.0.dist-info/WHEEL
pycololight-2.1.0.dist-info/METADATA
pycololight-2.1.0.dist-info/RECORD
